pyecho/__init__.py
pyecho/echo.py
pyecho-0.0.2.dist-info/DESCRIPTION.rst
pyecho-0.0.2.dist-info/METADATA
pyecho-0.0.2.dist-info/metadata.json
pyecho-0.0.2.dist-info/RECORD
pyecho-0.0.2.dist-info/top_level.txt
pyecho-0.0.2.dist-info/WHEEL
