Metadata-Version: 2.0
Name: pyecho
Version: 0.0.2
Summary: A micro library for retrying failing operations.
Home-page: http://github.com/itsnauman/echo
Author: Nauman Ahmad
Author-email: nauman-ahmad@outlook.com
License: MIT
Platform: UNKNOWN
